{"pageNumber":262,"juzNumber":14,"verses":[{"key":"15:1","surahNumber":15,"ayahNumber":1,"juzNumber":14,"pageNumber":262,"arabicText":"بِسْمِ ٱللَّهِ ٱلرَّحْمَٰنِ ٱلرَّحِيمِ الٓر ۚ تِلْكَ ءَايَٰتُ ٱلْكِتَٰبِ وَقُرْءَانٍۢ مُّبِينٍۢ","translationText":"Алиф. Лам. Ра. Это - аяты Писания и ясного Корана."},{"key":"15:2","surahNumber":15,"ayahNumber":2,"juzNumber":14,"pageNumber":262,"arabicText":"رُّبَمَا يَوَدُّ ٱلَّذِينَ كَفَرُوا۟ لَوْ كَانُوا۟ مُسْلِمِينَ","translationText":"Неверующие непременно пожелают оказаться мусульманами."},{"key":"15:3","surahNumber":15,"ayahNumber":3,"juzNumber":14,"pageNumber":262,"arabicText":"ذَرْهُمْ يَأْكُلُوا۟ وَيَتَمَتَّعُوا۟ وَيُلْهِهِمُ ٱلْأَمَلُ ۖ فَسَوْفَ يَعْلَمُونَ","translationText":"Оставь их - пусть они едят, пользуются благами и увлекаются чаяниями. Скоро они узнают."},{"key":"15:4","surahNumber":15,"ayahNumber":4,"juzNumber":14,"pageNumber":262,"arabicText":"وَمَآ أَهْلَكْنَا مِن قَرْيَةٍ إِلَّا وَلَهَا كِتَابٌۭ مَّعْلُومٌۭ","translationText":"Все селения, которые Мы погубили, имели известное предписание."},{"key":"15:5","surahNumber":15,"ayahNumber":5,"juzNumber":14,"pageNumber":262,"arabicText":"مَّا تَسْبِقُ مِنْ أُمَّةٍ أَجَلَهَا وَمَا يَسْتَـْٔخِرُونَ","translationText":"Ни одна община не может опередить свой срок или отложить его."},{"key":"15:6","surahNumber":15,"ayahNumber":6,"juzNumber":14,"pageNumber":262,"arabicText":"وَقَالُوا۟ يَٰٓأَيُّهَا ٱلَّذِى نُزِّلَ عَلَيْهِ ٱلذِّكْرُ إِنَّكَ لَمَجْنُونٌۭ","translationText":"Они сказали: «О тот, кому ниспослано откровение! Воистину, ты - одержимый."},{"key":"15:7","surahNumber":15,"ayahNumber":7,"juzNumber":14,"pageNumber":262,"arabicText":"لَّوْ مَا تَأْتِينَا بِٱلْمَلَٰٓئِكَةِ إِن كُنتَ مِنَ ٱلصَّٰدِقِينَ","translationText":"Почему ты не привел к нам ангелов, если ты - один из тех, кто говорит правду?»."},{"key":"15:8","surahNumber":15,"ayahNumber":8,"juzNumber":14,"pageNumber":262,"arabicText":"مَا نُنَزِّلُ ٱلْمَلَٰٓئِكَةَ إِلَّا بِٱلْحَقِّ وَمَا كَانُوٓا۟ إِذًۭا مُّنظَرِينَ","translationText":"Мы ниспосылаем ангелов только с истиной, и тогда никому не предоставляется отсрочка."},{"key":"15:9","surahNumber":15,"ayahNumber":9,"juzNumber":14,"pageNumber":262,"arabicText":"إِنَّا نَحْنُ نَزَّلْنَا ٱلذِّكْرَ وَإِنَّا لَهُۥ لَحَٰفِظُونَ","translationText":"Воистину, Мы ниспослали Напоминание, и Мы оберегаем его."},{"key":"15:10","surahNumber":15,"ayahNumber":10,"juzNumber":14,"pageNumber":262,"arabicText":"وَلَقَدْ أَرْسَلْنَا مِن قَبْلِكَ فِى شِيَعِ ٱلْأَوَّلِينَ","translationText":"Мы уже отправляли до тебя посланников к прежним общинам."},{"key":"15:11","surahNumber":15,"ayahNumber":11,"juzNumber":14,"pageNumber":262,"arabicText":"وَمَا يَأْتِيهِم مِّن رَّسُولٍ إِلَّا كَانُوا۟ بِهِۦ يَسْتَهْزِءُونَ","translationText":"Какой бы посланник ни приходил к ним, они издевались над ним."},{"key":"15:12","surahNumber":15,"ayahNumber":12,"juzNumber":14,"pageNumber":262,"arabicText":"كَذَٰلِكَ نَسْلُكُهُۥ فِى قُلُوبِ ٱلْمُجْرِمِينَ","translationText":"Таким же образом Мы насаждаем его (неверие) в сердцах грешников."},{"key":"15:13","surahNumber":15,"ayahNumber":13,"juzNumber":14,"pageNumber":262,"arabicText":"لَا يُؤْمِنُونَ بِهِۦ ۖ وَقَدْ خَلَتْ سُنَّةُ ٱلْأَوَّلِينَ","translationText":"Они не веруют в него (Коран), хотя уже были примеры первых поколений."},{"key":"15:14","surahNumber":15,"ayahNumber":14,"juzNumber":14,"pageNumber":262,"arabicText":"وَلَوْ فَتَحْنَا عَلَيْهِم بَابًۭا مِّنَ ٱلسَّمَآءِ فَظَلُّوا۟ فِيهِ يَعْرُجُونَ","translationText":"И даже если бы Мы разверзли для них врата небесные, чтобы они поднялись туда,"},{"key":"15:15","surahNumber":15,"ayahNumber":15,"juzNumber":14,"pageNumber":262,"arabicText":"لَقَالُوٓا۟ إِنَّمَا سُكِّرَتْ أَبْصَٰرُنَا بَلْ نَحْنُ قَوْمٌۭ مَّسْحُورُونَ","translationText":"они непременно сказали бы: «Наши взоры затуманены, а сами мы околдованы»."}],"translationEditionUsed":"ru.kuliev"}