{"pageNumber":311,"juzNumber":16,"verses":[{"key":"19:77","surahNumber":19,"ayahNumber":77,"juzNumber":16,"pageNumber":311,"arabicText":"أَفَرَءَيْتَ ٱلَّذِى كَفَرَ بِـَٔايَٰتِنَا وَقَالَ لَأُوتَيَنَّ مَالًۭا وَوَلَدًا","translationText":"Видел ли ты того, кто не уверовал в Наши знамения и сказал: «Я непременно буду одарен богатством и детьми?»."},{"key":"19:78","surahNumber":19,"ayahNumber":78,"juzNumber":16,"pageNumber":311,"arabicText":"أَطَّلَعَ ٱلْغَيْبَ أَمِ ٱتَّخَذَ عِندَ ٱلرَّحْمَٰنِ عَهْدًۭا","translationText":"Разве он знал сокровенное или заключил завет с Милостивым?"},{"key":"19:79","surahNumber":19,"ayahNumber":79,"juzNumber":16,"pageNumber":311,"arabicText":"كَلَّا ۚ سَنَكْتُبُ مَا يَقُولُ وَنَمُدُّ لَهُۥ مِنَ ٱلْعَذَابِ مَدًّۭا","translationText":"Нет! Мы запишем его слова и увеличим его мучения."},{"key":"19:80","surahNumber":19,"ayahNumber":80,"juzNumber":16,"pageNumber":311,"arabicText":"وَنَرِثُهُۥ مَا يَقُولُ وَيَأْتِينَا فَرْدًۭا","translationText":"Мы унаследуем от него то, о чем он говорил, и он явится к Нам в одиночестве."},{"key":"19:81","surahNumber":19,"ayahNumber":81,"juzNumber":16,"pageNumber":311,"arabicText":"وَٱتَّخَذُوا۟ مِن دُونِ ٱللَّهِ ءَالِهَةًۭ لِّيَكُونُوا۟ لَهُمْ عِزًّۭا","translationText":"Они стали поклоняться наряду с Аллахом другим богам, чтобы те одарили их могуществом."},{"key":"19:82","surahNumber":19,"ayahNumber":82,"juzNumber":16,"pageNumber":311,"arabicText":"كَلَّا ۚ سَيَكْفُرُونَ بِعِبَادَتِهِمْ وَيَكُونُونَ عَلَيْهِمْ ضِدًّا","translationText":"Но нет! Они отрекутся от поклонения им и станут их противниками."},{"key":"19:83","surahNumber":19,"ayahNumber":83,"juzNumber":16,"pageNumber":311,"arabicText":"أَلَمْ تَرَ أَنَّآ أَرْسَلْنَا ٱلشَّيَٰطِينَ عَلَى ٱلْكَٰفِرِينَ تَؤُزُّهُمْ أَزًّۭا","translationText":"Разве ты не видишь, что Мы послали к неверующим дьяволов, чтобы те подстрекали их?"},{"key":"19:84","surahNumber":19,"ayahNumber":84,"juzNumber":16,"pageNumber":311,"arabicText":"فَلَا تَعْجَلْ عَلَيْهِمْ ۖ إِنَّمَا نَعُدُّ لَهُمْ عَدًّۭا","translationText":"Посему не торопись с ними! Мы ведем для них счет."},{"key":"19:85","surahNumber":19,"ayahNumber":85,"juzNumber":16,"pageNumber":311,"arabicText":"يَوْمَ نَحْشُرُ ٱلْمُتَّقِينَ إِلَى ٱلرَّحْمَٰنِ وَفْدًۭا","translationText":"В тот день Мы соберем благочестивых перед Милостивым почтенной делегацией,"},{"key":"19:86","surahNumber":19,"ayahNumber":86,"juzNumber":16,"pageNumber":311,"arabicText":"وَنَسُوقُ ٱلْمُجْرِمِينَ إِلَىٰ جَهَنَّمَ وِرْدًۭا","translationText":"а грешников погоним в Геенну, словно на водопой."},{"key":"19:87","surahNumber":19,"ayahNumber":87,"juzNumber":16,"pageNumber":311,"arabicText":"لَّا يَمْلِكُونَ ٱلشَّفَٰعَةَ إِلَّا مَنِ ٱتَّخَذَ عِندَ ٱلرَّحْمَٰنِ عَهْدًۭا","translationText":"Никто не обретет права заступничества, кроме тех, у кого был завет с Аллахом."},{"key":"19:88","surahNumber":19,"ayahNumber":88,"juzNumber":16,"pageNumber":311,"arabicText":"وَقَالُوا۟ ٱتَّخَذَ ٱلرَّحْمَٰنُ وَلَدًۭا","translationText":"Они говорят: «Милостивый взял Себе сына»."},{"key":"19:89","surahNumber":19,"ayahNumber":89,"juzNumber":16,"pageNumber":311,"arabicText":"لَّقَدْ جِئْتُمْ شَيْـًٔا إِدًّۭا","translationText":"Этим вы совершаете ужасное злодеяние."},{"key":"19:90","surahNumber":19,"ayahNumber":90,"juzNumber":16,"pageNumber":311,"arabicText":"تَكَادُ ٱلسَّمَٰوَٰتُ يَتَفَطَّرْنَ مِنْهُ وَتَنشَقُّ ٱلْأَرْضُ وَتَخِرُّ ٱلْجِبَالُ هَدًّا","translationText":"Небо готово расколоться, земля готова разверзнуться, а горы готовы рассыпаться в прах от того,"},{"key":"19:91","surahNumber":19,"ayahNumber":91,"juzNumber":16,"pageNumber":311,"arabicText":"أَن دَعَوْا۟ لِلرَّحْمَٰنِ وَلَدًۭا","translationText":"что они приписывают Милостивому сына."},{"key":"19:92","surahNumber":19,"ayahNumber":92,"juzNumber":16,"pageNumber":311,"arabicText":"وَمَا يَنۢبَغِى لِلرَّحْمَٰنِ أَن يَتَّخِذَ وَلَدًا","translationText":"Не подобает Милостивому иметь сына!"},{"key":"19:93","surahNumber":19,"ayahNumber":93,"juzNumber":16,"pageNumber":311,"arabicText":"إِن كُلُّ مَن فِى ٱلسَّمَٰوَٰتِ وَٱلْأَرْضِ إِلَّآ ءَاتِى ٱلرَّحْمَٰنِ عَبْدًۭا","translationText":"Каждый, кто на небесах и на земле, явится к Милостивому только в качестве раба."},{"key":"19:94","surahNumber":19,"ayahNumber":94,"juzNumber":16,"pageNumber":311,"arabicText":"لَّقَدْ أَحْصَىٰهُمْ وَعَدَّهُمْ عَدًّۭا","translationText":"Он знает их число и пересчитал их."},{"key":"19:95","surahNumber":19,"ayahNumber":95,"juzNumber":16,"pageNumber":311,"arabicText":"وَكُلُّهُمْ ءَاتِيهِ يَوْمَ ٱلْقِيَٰمَةِ فَرْدًا","translationText":"Каждый из них явится к Нему в День воскресения в одиночестве."}],"translationEditionUsed":"ru.kuliev"}