{"pageNumber":452,"juzNumber":23,"verses":[{"key":"37:154","surahNumber":37,"ayahNumber":154,"juzNumber":23,"pageNumber":452,"arabicText":"مَا لَكُمْ كَيْفَ تَحْكُمُونَ","translationText":"Was verwirrt euch? Wie urteilt ihr nur?"},{"key":"37:155","surahNumber":37,"ayahNumber":155,"juzNumber":23,"pageNumber":452,"arabicText":"أَفَلَا تَذَكَّرُونَ","translationText":"Wollt ihr euch denn nicht besinnen?"},{"key":"37:156","surahNumber":37,"ayahNumber":156,"juzNumber":23,"pageNumber":452,"arabicText":"أَمْ لَكُمْ سُلْطَٰنٌۭ مُّبِينٌۭ","translationText":"Oder habt ihr einen klaren Beweis?"},{"key":"37:157","surahNumber":37,"ayahNumber":157,"juzNumber":23,"pageNumber":452,"arabicText":"فَأْتُوا۟ بِكِتَٰبِكُمْ إِن كُنتُمْ صَٰدِقِينَ","translationText":"Sodann bringt euer Buch herbei, wenn ihr wahrhaftig seid."},{"key":"37:158","surahNumber":37,"ayahNumber":158,"juzNumber":23,"pageNumber":452,"arabicText":"وَجَعَلُوا۟ بَيْنَهُۥ وَبَيْنَ ٱلْجِنَّةِ نَسَبًۭا ۚ وَلَقَدْ عَلِمَتِ ٱلْجِنَّةُ إِنَّهُمْ لَمُحْضَرُونَ","translationText":"Und sie unterstellten Ihm eine Blutsverwandschaft mit den Ginn; während die Ginn doch recht wohl wissen, daß sie (vor Ihn zum Gericht) gebracht werden sollen."},{"key":"37:159","surahNumber":37,"ayahNumber":159,"juzNumber":23,"pageNumber":452,"arabicText":"سُبْحَٰنَ ٱللَّهِ عَمَّا يَصِفُونَ","translationText":"Gepriesen sei Allah hoch über all das, was sie beschreiben."},{"key":"37:160","surahNumber":37,"ayahNumber":160,"juzNumber":23,"pageNumber":452,"arabicText":"إِلَّا عِبَادَ ٱللَّهِ ٱلْمُخْلَصِينَ","translationText":"Ausgenommen (davon sind) die erwählten Diener Allahs."},{"key":"37:161","surahNumber":37,"ayahNumber":161,"juzNumber":23,"pageNumber":452,"arabicText":"فَإِنَّكُمْ وَمَا تَعْبُدُونَ","translationText":"Wahrlich, ihr und das, was ihr verehrt"},{"key":"37:162","surahNumber":37,"ayahNumber":162,"juzNumber":23,"pageNumber":452,"arabicText":"مَآ أَنتُمْ عَلَيْهِ بِفَٰتِنِينَ","translationText":"ihr vermögt nicht (einen) gegen Ihn zu verführen"},{"key":"37:163","surahNumber":37,"ayahNumber":163,"juzNumber":23,"pageNumber":452,"arabicText":"إِلَّا مَنْ هُوَ صَالِ ٱلْجَحِيمِ","translationText":"mit Ausnahme dessen, der in der Gahim brennen wird."},{"key":"37:164","surahNumber":37,"ayahNumber":164,"juzNumber":23,"pageNumber":452,"arabicText":"وَمَا مِنَّآ إِلَّا لَهُۥ مَقَامٌۭ مَّعْلُومٌۭ","translationText":"Und da ist keiner unter uns (Engeln), der nicht seinen (ihm) zugewiesenen Platz hätte."},{"key":"37:165","surahNumber":37,"ayahNumber":165,"juzNumber":23,"pageNumber":452,"arabicText":"وَإِنَّا لَنَحْنُ ٱلصَّآفُّونَ","translationText":"Und wahrlich, wir sind die in Reihen Geordneten."},{"key":"37:166","surahNumber":37,"ayahNumber":166,"juzNumber":23,"pageNumber":452,"arabicText":"وَإِنَّا لَنَحْنُ ٱلْمُسَبِّحُونَ","translationText":"Und wahrlich, wir sind es, die (Allah) preisen."},{"key":"37:167","surahNumber":37,"ayahNumber":167,"juzNumber":23,"pageNumber":452,"arabicText":"وَإِن كَانُوا۟ لَيَقُولُونَ","translationText":"Und sie pflegten doch zu sagen"},{"key":"37:168","surahNumber":37,"ayahNumber":168,"juzNumber":23,"pageNumber":452,"arabicText":"لَوْ أَنَّ عِندَنَا ذِكْرًۭا مِّنَ ٱلْأَوَّلِينَ","translationText":"\"Hätten wir nur eine Mahnung von Seiten der Früheren (erhalten)"},{"key":"37:169","surahNumber":37,"ayahNumber":169,"juzNumber":23,"pageNumber":452,"arabicText":"لَكُنَّا عِبَادَ ٱللَّهِ ٱلْمُخْلَصِينَ","translationText":"so wären wir sicher Allahs erwählte Diener gewesen.\""},{"key":"37:170","surahNumber":37,"ayahNumber":170,"juzNumber":23,"pageNumber":452,"arabicText":"فَكَفَرُوا۟ بِهِۦ ۖ فَسَوْفَ يَعْلَمُونَ","translationText":"Dennoch glauben sie nicht an ihn (den Quran), allein sie werden es bald erfahren."},{"key":"37:171","surahNumber":37,"ayahNumber":171,"juzNumber":23,"pageNumber":452,"arabicText":"وَلَقَدْ سَبَقَتْ كَلِمَتُنَا لِعِبَادِنَا ٱلْمُرْسَلِينَ","translationText":"Wahrlich, Unser Wort ist schon an Unsere gesandten Diener ergangen"},{"key":"37:172","surahNumber":37,"ayahNumber":172,"juzNumber":23,"pageNumber":452,"arabicText":"إِنَّهُمْ لَهُمُ ٱلْمَنصُورُونَ","translationText":"sie sind wahrlich die, denen geholfen wird."},{"key":"37:173","surahNumber":37,"ayahNumber":173,"juzNumber":23,"pageNumber":452,"arabicText":"وَإِنَّ جُندَنَا لَهُمُ ٱلْغَٰلِبُونَ","translationText":"Und Unsere Heerschar wird sicher siegreich sein."},{"key":"37:174","surahNumber":37,"ayahNumber":174,"juzNumber":23,"pageNumber":452,"arabicText":"فَتَوَلَّ عَنْهُمْ حَتَّىٰ حِينٍۢ","translationText":"Darum wende dich von ihnen für eine Zeitlang ab"},{"key":"37:175","surahNumber":37,"ayahNumber":175,"juzNumber":23,"pageNumber":452,"arabicText":"وَأَبْصِرْهُمْ فَسَوْفَ يُبْصِرُونَ","translationText":"und beobachte sie; denn sie werden bald sehen."},{"key":"37:176","surahNumber":37,"ayahNumber":176,"juzNumber":23,"pageNumber":452,"arabicText":"أَفَبِعَذَابِنَا يَسْتَعْجِلُونَ","translationText":"Ist es etwa Unsere Strafe, die sie beschleunigen möchten?"},{"key":"37:177","surahNumber":37,"ayahNumber":177,"juzNumber":23,"pageNumber":452,"arabicText":"فَإِذَا نَزَلَ بِسَاحَتِهِمْ فَسَآءَ صَبَاحُ ٱلْمُنذَرِينَ","translationText":"Doch wenn sie über ihr Gebiet herabkommt, dann wird der Morgen für die Gewarnten übel sein."},{"key":"37:178","surahNumber":37,"ayahNumber":178,"juzNumber":23,"pageNumber":452,"arabicText":"وَتَوَلَّ عَنْهُمْ حَتَّىٰ حِينٍۢ","translationText":"So wende dich von ihnen für eine Zeitlang ab"},{"key":"37:179","surahNumber":37,"ayahNumber":179,"juzNumber":23,"pageNumber":452,"arabicText":"وَأَبْصِرْ فَسَوْفَ يُبْصِرُونَ","translationText":"und beobachte (sie); denn sie werden bald sehen."},{"key":"37:180","surahNumber":37,"ayahNumber":180,"juzNumber":23,"pageNumber":452,"arabicText":"سُبْحَٰنَ رَبِّكَ رَبِّ ٱلْعِزَّةِ عَمَّا يَصِفُونَ","translationText":"Gepriesen sei dein Herr, der Herr der Erhabenheit, Hoch über dem, was sie beschreiben."},{"key":"37:181","surahNumber":37,"ayahNumber":181,"juzNumber":23,"pageNumber":452,"arabicText":"وَسَلَٰمٌ عَلَى ٱلْمُرْسَلِينَ","translationText":"Und Friede sei auf den Gesandten!"},{"key":"37:182","surahNumber":37,"ayahNumber":182,"juzNumber":23,"pageNumber":452,"arabicText":"وَٱلْحَمْدُ لِلَّهِ رَبِّ ٱلْعَٰلَمِينَ","translationText":"Und alles Lob gebührt Allah, dem Herrn der Welten."}],"translationEditionUsed":"de.aburida"}